README.md
setup.py
pokeronline/__init__.py
pokeronline/authorization.py
pokeronline/friend.py
pokeronline/game.py
pokeronline/pokeronline.py
pokeronline/socket_listener.py
pokeronline.py.egg-info/PKG-INFO
pokeronline.py.egg-info/SOURCES.txt
pokeronline.py.egg-info/dependency_links.txt
pokeronline.py.egg-info/requires.txt
pokeronline.py.egg-info/top_level.txt
pokeronline/utils/__init__.py
pokeronline/utils/objects.py