Metadata-Version: 2.1
Name: pokeronline.py
Version: 1.0.0
Summary: A library to create Poker Online bots.
Home-page: https://github.com/Zakovskiy/pokeronline.py
Author: Zakovskiy
Author-email: gogrugu@gmail.com
License: MIT
Download-URL: https://github.com/Zakovskiy/pokeronline.py/tarball/master
Keywords: durak,online,pokeronline,pokeronline.py,pokeronline-bot,rstgame,rstgames,api,socket,python,python3,python3.x,zakovskiy,official
Platform: UNKNOWN
